{"annotation":{"filename":"ADE_train_00004782.jpg","folder":"ADE20K_2021_17_01/images/ADE/training/urban/building_facade","imsize":[256,256,3],"source":{"folder":"static_sun_database/b/building_facade","filename":"sun_avvykthuszatouwd.jpg","origin":"Downloaded from Google search. Image might be subject to copyright. Use only for non-commercial research and educational purposes."},"scene":["outdoor","urban","building_facade"],"object":[{"id":0,"name":"sky","name_ndx":2420,"hypernym":["sky","atmosphere","gas","fluid","matter","physical entity","entity"],"raw_name":"sky","attributes":[],"depth_ordering_rank":1,"occluded":[],"crop":"0","parts":{"hasparts":[],"ispartof":[],"part_level":0},"instance_mask":"ADE_train_00004782/instance_000_ADE_train_00004782.png","polygon":{"x":[2,2,134,121,127,126,93,93,90,81,81,47,13],"y":[45,1,1,15,22,43,47,27,25,26,40,11,48],"click_date":[]},"saved_date":"29-Nov-2006 16:38:01"},{"id":1,"name":"chimney","name_ndx":495,"hypernym":["chimney","flue","conduit","passage","way","artifact, artefact","whole, unit","object, physical object","physical entity","entity"],"raw_name":"chimney","attributes":[],"depth_ordering_rank":2,"occluded":[],"crop":"0","parts":{"hasparts":[],"ispartof":[],"part_level":0},"instance_mask":"ADE_train_00004782/instance_001_ADE_train_00004782.png","polygon":{"x":[85,82,82,91,93,93,92],"y":[43,40,25,25,28,46,50],"click_date":[]},"saved_date":"29-Nov-2006 16:38:01"},{"id":2,"name":"building, edifice","name_ndx":312,"hypernym":["building, edifice","structure, construction","artifact, artefact","whole, unit","object, physical object","physical entity","entity"],"raw_name":"building","attributes":[],"depth_ordering_rank":3,"occluded":[],"crop":"0","parts":{"hasparts":[9,10,11,14,15,17,18],"ispartof":[],"part_level":0},"instance_mask":"ADE_train_00004782/instance_002_ADE_train_00004782.png","polygon":{"x":[2,2,12,47,93,97,125,127,122,134,256,256,229,227,62,61],"y":[211,46,48,10,49,46,42,21,15,1,0,254,246,215,215,213],"click_date":[]},"saved_date":"29-Nov-2006 16:38:01"},{"id":3,"name":"grass","name_ndx":1125,"hypernym":["grass","gramineous plant, graminaceous plant","herb, herbaceous plant","vascular plant, tracheophyte","plant, flora, plant life","organism, being","living thing, animate thing","whole, unit","object, physical object","physical entity","entity"],"raw_name":"grass","attributes":[],"depth_ordering_rank":4,"occluded":[],"crop":"0","parts":{"hasparts":[],"ispartof":[],"part_level":0},"instance_mask":"ADE_train_00004782/instance_003_ADE_train_00004782.png","polygon":{"x":[0,0,46,2],"y":[221,210,212,219],"click_date":[]},"saved_date":"29-Nov-2006 16:38:01"},{"id":4,"name":"path","name_ndx":1788,"hypernym":["path","way","artifact, artefact","whole, unit","object, physical object","physical entity","entity"],"raw_name":"path","attributes":[],"depth_ordering_rank":5,"occluded":[],"crop":"0","parts":{"hasparts":[],"ispartof":[],"part_level":0},"instance_mask":"ADE_train_00004782/instance_004_ADE_train_00004782.png","polygon":{"x":[2,60,44,2],"y":[226,215,212,220],"click_date":[]},"saved_date":"29-Nov-2006 16:38:01"},{"id":5,"name":"grass","name_ndx":1125,"hypernym":["grass","gramineous plant, graminaceous plant","herb, herbaceous plant","vascular plant, tracheophyte","plant, flora, plant life","organism, being","living thing, animate thing","whole, unit","object, physical object","physical entity","entity"],"raw_name":"grass","attributes":[],"depth_ordering_rank":6,"occluded":[],"crop":"0","parts":{"hasparts":[],"ispartof":[],"part_level":0},"instance_mask":"ADE_train_00004782/instance_005_ADE_train_00004782.png","polygon":{"x":[0,2,61,226,229,256,256],"y":[256,227,215,216,246,254,256],"click_date":[]},"saved_date":"29-Nov-2006 16:38:01"},{"id":6,"name":"stairs, steps","name_ndx":2530,"hypernym":["stairs, steps","stairway, staircase","way","artifact, artefact","whole, unit","object, physical object","physical entity","entity"],"raw_name":"steps","attributes":[],"depth_ordering_rank":7,"occluded":[],"crop":"0","parts":{"hasparts":[],"ispartof":[],"part_level":0},"instance_mask":"ADE_train_00004782/instance_006_ADE_train_00004782.png","polygon":{"x":[102,96,96,89,89,83,83,77,77,70,70,65,65,102],"y":[190,190,194,195,200,200,203,203,208,208,213,212,214,214],"click_date":[]},"saved_date":"29-Nov-2006 16:38:01"},{"id":7,"name":"porch","name_ndx":1951,"hypernym":[],"raw_name":"porch","attributes":[],"depth_ordering_rank":8,"occluded":[],"crop":"0","parts":{"hasparts":[],"ispartof":[],"part_level":0},"instance_mask":"ADE_train_00004782/instance_007_ADE_train_00004782.png","polygon":{"x":[227,220,204,189,144,134,104,89,102,104,228],"y":[207,91,91,97,100,97,99,112,112,214,214],"click_date":[]},"saved_date":"29-Nov-2006 16:38:01"},{"id":8,"name":"bannister, banister, balustrade, balusters, handrail","name_ndx":120,"hypernym":["bannister, banister, balustrade, balusters, handrail","barrier","obstruction, obstructor, obstructer, impediment, impedimenta","structure, construction","artifact, artefact","whole, unit","object, physical object","physical entity","entity"],"raw_name":"handrail","attributes":[],"depth_ordering_rank":9,"occluded":[],"crop":"0","parts":{"hasparts":[],"ispartof":[],"part_level":0},"instance_mask":"ADE_train_00004782/instance_008_ADE_train_00004782.png","polygon":{"x":[110,163,162,166,168,162,162,222,224,223,106,105],"y":[167,165,106,106,212,212,166,163,163,184,185,167],"click_date":[]},"saved_date":"29-Nov-2006 16:38:01"},{"id":9,"name":"window","name_ndx":3050,"hypernym":[],"raw_name":"window","attributes":[],"depth_ordering_rank":10,"occluded":[],"crop":"0","parts":{"ispartof":2,"hasparts":[],"part_level":1},"instance_mask":"ADE_train_00004782/instance_009_ADE_train_00004782.png","polygon":{"x":[150,189,189,150],"y":[136,135,157,158],"click_date":[]},"saved_date":"29-Nov-2006 16:38:01"},{"id":10,"name":"window","name_ndx":3050,"hypernym":[],"raw_name":"window","attributes":[],"depth_ordering_rank":11,"occluded":[],"crop":"0","parts":{"ispartof":2,"hasparts":[],"part_level":1},"instance_mask":"ADE_train_00004782/instance_010_ADE_train_00004782.png","polygon":{"x":[81,81,90,90],"y":[159,142,142,159],"click_date":[]},"saved_date":"29-Nov-2006 16:38:01"},{"id":11,"name":"window","name_ndx":3050,"hypernym":[],"raw_name":"window","attributes":[],"depth_ordering_rank":12,"occluded":[],"crop":"0","parts":{"ispartof":2,"hasparts":[],"part_level":1},"instance_mask":"ADE_train_00004782/instance_011_ADE_train_00004782.png","polygon":{"x":[24,24,32,33],"y":[161,145,145,161],"click_date":[]},"saved_date":"29-Nov-2006 16:38:01"},{"id":12,"name":"pane, pane of glass, window glass","name_ndx":1747,"hypernym":["pane, pane of glass, window glass","plate glass, sheet glass","sheet, flat solid","artifact, artefact","whole, unit","object, physical object","physical entity","entity"],"raw_name":"pane","attributes":"glass","depth_ordering_rank":13,"occluded":[],"crop":"0","parts":{"hasparts":[],"ispartof":[],"part_level":0},"instance_mask":"ADE_train_00004782/instance_012_ADE_train_00004782.png","polygon":{"x":[54,54,7,8],"y":[125,139,141,128],"click_date":[]},"saved_date":"29-Nov-2006 16:38:01"},{"id":13,"name":"pane, pane of glass, window glass","name_ndx":1747,"hypernym":["pane, pane of glass, window glass","plate glass, sheet glass","sheet, flat solid","artifact, artefact","whole, unit","object, physical object","physical entity","entity"],"raw_name":"pane","attributes":"glass","depth_ordering_rank":14,"occluded":[],"crop":"0","parts":{"hasparts":[],"ispartof":[],"part_level":0},"instance_mask":"ADE_train_00004782/instance_013_ADE_train_00004782.png","polygon":{"x":[57,57,102,101],"y":[124,138,135,122],"click_date":[]},"saved_date":"29-Nov-2006 16:38:01"},{"id":14,"name":"window","name_ndx":3050,"hypernym":[],"raw_name":"window","attributes":[],"depth_ordering_rank":15,"occluded":[],"crop":"0","parts":{"ispartof":2,"hasparts":[],"part_level":1},"instance_mask":"ADE_train_00004782/instance_014_ADE_train_00004782.png","polygon":{"x":[29,30,44,44],"y":[79,63,62,78],"click_date":[]},"saved_date":"29-Nov-2006 16:38:01"},{"id":15,"name":"window","name_ndx":3050,"hypernym":[],"raw_name":"window","attributes":[],"depth_ordering_rank":16,"occluded":[],"crop":"0","parts":{"ispartof":2,"hasparts":[],"part_level":1},"instance_mask":"ADE_train_00004782/instance_015_ADE_train_00004782.png","polygon":{"x":[51,66,65,51],"y":[60,59,75,76],"click_date":[]},"saved_date":"29-Nov-2006 16:38:01"},{"id":16,"name":"pane, pane of glass, window glass","name_ndx":1747,"hypernym":["pane, pane of glass, window glass","plate glass, sheet glass","sheet, flat solid","artifact, artefact","whole, unit","object, physical object","physical entity","entity"],"raw_name":"pane","attributes":"glass","depth_ordering_rank":17,"occluded":[],"crop":"0","parts":{"hasparts":[],"ispartof":[],"part_level":0},"instance_mask":"ADE_train_00004782/instance_016_ADE_train_00004782.png","polygon":{"x":[29,39,59,69,68,28],"y":[54,42,41,49,55,59],"click_date":[]},"saved_date":"29-Nov-2006 16:38:01"},{"id":17,"name":"window","name_ndx":3050,"hypernym":[],"raw_name":"window","attributes":[],"depth_ordering_rank":18,"occluded":[],"crop":"0","parts":{"ispartof":2,"hasparts":[],"part_level":1},"instance_mask":"ADE_train_00004782/instance_017_ADE_train_00004782.png","polygon":{"x":[158,160,162,167,169,170,169,167,163,161],"y":[72,68,66,66,67,70,75,77,77,75],"click_date":[]},"saved_date":"29-Nov-2006 16:38:01"},{"id":18,"name":"window","name_ndx":3050,"hypernym":[],"raw_name":"window","attributes":[],"depth_ordering_rank":19,"occluded":[],"crop":"0","parts":{"ispartof":2,"hasparts":[],"part_level":1},"instance_mask":"ADE_train_00004782/instance_018_ADE_train_00004782.png","polygon":{"x":[250,249,228,230],"y":[139,109,114,142],"click_date":[]},"saved_date":"29-Nov-2006 16:38:01"}]}}